{
  "asset": "DE40",
  "created_utc": "2026-05-16T08:29:42+00:00",
  "source": "BOT_PIVOT_02_zones.py",
  "version": "02.4_global_local_psycho_confluence",
  "method": "global_30d_local_3d_tpo_atr_psychological_levels",
  "history_resolution": "MINUTE_15",
  "history_days": 30,
  "local_days": 3,
  "candles_30d_count": 2096,
  "candles_local_count": 289,
  "last_close": 23994.35,
  "atr_period": 96,
  "atr_global_m15": 37.735417,
  "atr_local_m15": 37.735417,
  "psycho_steps": {
    "target": 301.88333333,
    "minor": 200,
    "medium": 500,
    "major": 1000
  },
  "global_profile": {
    "price_min": 23617.35,
    "price_max": 25152.95,
    "bucket_count": 406,
    "bucket_width": 3.78226601,
    "candidates_count": 12
  },
  "local_profile": {
    "price_min": 23925.35,
    "price_max": 24495.85,
    "bucket_count": 400,
    "bucket_width": 1.42625,
    "candidates_count": 38
  },
  "psycho_candidates_count": 11,
  "zones_count": 8,
  "supports_count": 3,
  "resistances_count": 4,
  "active_count": 1,
  "local_zones_count": 3,
  "major_zones_count": 3,
  "psycho_zones_count": 8,
  "confluence_count": 5,
  "rules": {
    "local_days": 3,
    "zone_min_atr": 0.6,
    "zone_max_atr": 2.3,
    "center_min_distance_atr": 0.95,
    "local_near_distance_atr": 10.0,
    "psycho_target_atr": 8.0,
    "psycho_scan_atr": 25.0,
    "psycho_minor_width_atr": 0.85,
    "psycho_major_width_atr": 1.05,
    "psycho_big_width_atr": 1.25
  },
  "zones": [
    {
      "scope": "PSYCHO",
      "base_scope": "PSYCHO",
      "type": "support",
      "low": 23183.962448,
      "high": 23216.037552,
      "center": 23200,
      "width": 32.075104,
      "atr": 37.735417,
      "width_atr": 0.85,
      "strength": 450,
      "peak_count": 0,
      "peak_smoothed": 0.0,
      "bucket_index": null,
      "distance_points_from_last_close": -794.35,
      "distance_atr_from_last_close": -21.0505,
      "distance_pct_from_last_close": -0.033106,
      "confluence": false,
      "psycho_level": 23200,
      "psycho_rank": "MINOR",
      "psycho_step": 200,
      "score": 957.5,
      "rank_by_price": 1
    },
    {
      "scope": "PSYCHO",
      "base_scope": "PSYCHO",
      "type": "support",
      "low": 23583.962448,
      "high": 23616.037552,
      "center": 23600,
      "width": 32.075104,
      "atr": 37.735417,
      "width_atr": 0.85,
      "strength": 450,
      "peak_count": 0,
      "peak_smoothed": 0.0,
      "bucket_index": null,
      "distance_points_from_last_close": -394.35,
      "distance_atr_from_last_close": -10.4504,
      "distance_pct_from_last_close": -0.016435,
      "confluence": false,
      "psycho_level": 23600,
      "psycho_rank": "MINOR",
      "psycho_step": 200,
      "score": 996.2401,
      "rank_by_price": 2
    },
    {
      "scope": "PSYCHO",
      "base_scope": "PSYCHO",
      "type": "support",
      "low": 23783.962448,
      "high": 23816.037552,
      "center": 23800,
      "width": 32.075104,
      "atr": 37.735417,
      "width_atr": 0.85,
      "strength": 450,
      "peak_count": 0,
      "peak_smoothed": 0.0,
      "bucket_index": null,
      "distance_points_from_last_close": -194.35,
      "distance_atr_from_last_close": -5.1503,
      "distance_pct_from_last_close": -0.0081,
      "confluence": false,
      "psycho_level": 23800,
      "psycho_rank": "MINOR",
      "psycho_step": 200,
      "score": 1128.7416,
      "rank_by_price": 3
    },
    {
      "scope": "LOCAL+PSYCHO",
      "base_scope": "LOCAL+PSYCHO",
      "type": "active",
      "low": 23958.15375,
      "high": 24023.584635,
      "center": 23997.940757,
      "width": 65.430885,
      "atr": 37.735417,
      "width_atr": 1.7339,
      "strength": 997,
      "peak_count": 14,
      "peak_smoothed": 14.2,
      "bucket_index": null,
      "distance_points_from_last_close": 3.590757,
      "distance_atr_from_last_close": 0.0952,
      "distance_pct_from_last_close": 0.00015,
      "confluence": true,
      "psycho_level": 24000,
      "psycho_rank": "BIG",
      "psycho_step": 1000,
      "score": 2746.5711,
      "rank_by_price": 4
    },
    {
      "scope": "LOCAL+PSYCHO",
      "base_scope": "LOCAL+PSYCHO",
      "type": "resistance",
      "low": 24008.0725,
      "high": 24071.45125,
      "center": 24040.606785,
      "width": 63.37875,
      "atr": 37.735417,
      "width_atr": 1.6796,
      "strength": 1527,
      "peak_count": 35,
      "peak_smoothed": 34.2,
      "bucket_index": 71,
      "distance_points_from_last_close": 46.256785,
      "distance_atr_from_last_close": 1.2258,
      "distance_pct_from_last_close": 0.001928,
      "confluence": true,
      "psycho_level": 24000,
      "psycho_rank": "BIG",
      "psycho_step": 1000,
      "score": 2719.3545,
      "rank_by_price": 5
    },
    {
      "scope": "MAJOR+PSYCHO+LOCAL",
      "base_scope": "MAJOR+PSYCHO+LOCAL",
      "type": "resistance",
      "low": 24087.30514,
      "high": 24174.096598,
      "center": 24130.700869,
      "width": 86.791458,
      "atr": 37.735417,
      "width_atr": 2.3,
      "strength": 2697,
      "peak_count": 214,
      "peak_smoothed": 213.0,
      "bucket_index": 138,
      "distance_points_from_last_close": 136.350869,
      "distance_atr_from_last_close": 3.6133,
      "distance_pct_from_last_close": 0.005683,
      "confluence": true,
      "psycho_level": 24200,
      "psycho_rank": "MINOR",
      "psycho_step": 200,
      "score": 2359.6665,
      "rank_by_price": 6
    },
    {
      "scope": "MAJOR+PSYCHO",
      "base_scope": "MAJOR+PSYCHO",
      "type": "resistance",
      "low": 24377.585468,
      "high": 24416.037552,
      "center": 24396.882823,
      "width": 38.452084,
      "atr": 37.735417,
      "width_atr": 1.019,
      "strength": 1066,
      "peak_count": 88,
      "peak_smoothed": 89.4,
      "bucket_index": 206,
      "distance_points_from_last_close": 402.532823,
      "distance_atr_from_last_close": 10.6672,
      "distance_pct_from_last_close": 0.016776,
      "confluence": true,
      "psycho_level": 24400,
      "psycho_rank": "MINOR",
      "psycho_step": 200,
      "score": 1533.3189,
      "rank_by_price": 7
    },
    {
      "scope": "MAJOR+PSYCHO",
      "base_scope": "MAJOR+PSYCHO",
      "type": "resistance",
      "low": 24895.755911,
      "high": 24978.965764,
      "center": 24937.360837,
      "width": 83.209852,
      "atr": 37.735417,
      "width_atr": 2.2051,
      "strength": 618,
      "peak_count": 48,
      "peak_smoothed": 45.4,
      "bucket_index": 348,
      "distance_points_from_last_close": 943.010837,
      "distance_atr_from_last_close": 24.9901,
      "distance_pct_from_last_close": 0.039301,
      "confluence": true,
      "psycho_level": 25000,
      "psycho_rank": "BIG",
      "psycho_step": 1000,
      "score": 1666.3,
      "rank_by_price": 8
    }
  ],
  "history_file": "/home/philippe_vacher06/bot-pivot/live/data/history/DE40_MINUTE_15_30d.json",
  "history_from_utc": "2026-04-15T13:28:00",
  "history_to_utc": "2026-05-15T13:28:00"
}